django_zarr_audio/__init__.py
django_zarr_audio/admin.py
django_zarr_audio/apps.py
django_zarr_audio/credentials.py
django_zarr_audio/models.py
django_zarr_audio/tasks.py
django_zarr_audio/urls.py
django_zarr_audio/utils.py
django_zarr_audio/views.py
django_zarr_audio/migrations/0001_initial.py
django_zarr_audio/migrations/0002_alter_audiofile_unique_together.py
django_zarr_audio/migrations/__init__.py
django_zarr_audio/templates/django_zarr_audio/list_fsspec_files.html
django_zarr_audio-0.3.0.dist-info/licenses/LICENSE
django_zarr_audio-0.3.0.dist-info/METADATA
django_zarr_audio-0.3.0.dist-info/WHEEL
django_zarr_audio-0.3.0.dist-info/top_level.txt
django_zarr_audio-0.3.0.dist-info/RECORD
