Metadata-Version: 2.4
Name: django-zarr-audio
Version: 0.3.0
Summary: Reusable Django app for working with audio and Zarr
Author-email: Joe Weiss <joe.weiss@gmail.com>
License:                                  Apache License
Project-URL: Homepage, https://github.com/joeweiss/django-zarr-audio
Project-URL: Repository, https://github.com/joeweiss/django-zarr-audio
Classifier: Framework :: Django
Classifier: Programming Language :: Python :: 3
Classifier: License :: OSI Approved :: Apache Software License
Requires-Python: >=3.8
License-File: LICENSE
Requires-Dist: Django>=4.2
Requires-Dist: zarr-audio
Requires-Dist: django-model-utils
Requires-Dist: huey
Provides-Extra: dev
Requires-Dist: tox; extra == "dev"
Requires-Dist: pytest; extra == "dev"
Requires-Dist: pytest-django; extra == "dev"
Requires-Dist: black; extra == "dev"
Requires-Dist: isort; extra == "dev"
Requires-Dist: mypy; extra == "dev"
Requires-Dist: watchdog; extra == "dev"
Requires-Dist: boto3; extra == "dev"
Requires-Dist: dotenv; extra == "dev"
Dynamic: license-file
